openassistants/__init__.py
openassistants/contrib/advisor_function.py
openassistants/contrib/duckdb_query.py
openassistants/contrib/index_function.py
openassistants/contrib/langchain_ddg_tool.py
openassistants/contrib/python_callable.py
openassistants/contrib/python_eval.py
openassistants/contrib/sqlalchemy_query.py
openassistants/contrib/text_response.py
openassistants/core/assistant.py
openassistants/data_models/__init__.py
openassistants/data_models/chat_messages.py
openassistants/data_models/function_input.py
openassistants/data_models/function_output.py
openassistants/data_models/json_schema.py
openassistants/data_models/serialized_dataframe.py
openassistants/eval/base.py
openassistants/eval/checks/function_infilling.py
openassistants/eval/checks/function_selection.py
openassistants/eval/interaction.py
openassistants/functions/base.py
openassistants/functions/crud.py
openassistants/functions/utils.py
openassistants/functions/visualize.py
openassistants/llm_function_calling/entity_resolution.py
openassistants/llm_function_calling/fallback.py
openassistants/llm_function_calling/infilling.py
openassistants/llm_function_calling/selection.py
openassistants/llm_function_calling/utils.py
openassistants/py.typed
openassistants/utils/async_utils.py
openassistants/utils/history_representation.py
openassistants/utils/json_schema.py
openassistants/utils/langchain_util.py
openassistants/utils/strings.py
openassistants/utils/vision.py
openassistants/utils/yaml.py
definitive_openassistants-0.0.14.dist-info/METADATA
definitive_openassistants-0.0.14.dist-info/WHEEL
definitive_openassistants-0.0.14.dist-info/RECORD
