Metadata-Version: 2.1
Name: definitive-openassistants
Version: 0.0.14
Summary: 
Author: Rick Lamers
Author-email: ricklamers@gmail.com
Requires-Python: >=3.10,<3.12
Classifier: Programming Language :: Python :: 3
Classifier: Programming Language :: Python :: 3.10
Classifier: Programming Language :: Python :: 3.11
Provides-Extra: duckdb
Provides-Extra: duckduckgo
Provides-Extra: sql
Requires-Dist: duckdb-engine (>=0.9.3,<0.10.0) ; extra == "duckdb"
Requires-Dist: duckduckgo-search (>=3.9.11,<4.0.0) ; extra == "duckduckgo"
Requires-Dist: fastapi (>=0.109.2,<0.110.0)
Requires-Dist: jsonschema (>=4.20.0,<5.0.0)
Requires-Dist: langchain (>=0.0.352,<0.0.353)
Requires-Dist: langchain-community (>=0.0.6,<0.0.7)
Requires-Dist: openai (>=1.3.7,<2.0.0)
Requires-Dist: openapi-pydantic (>=0.3.2,<0.4.0)
Requires-Dist: pandas (>=2.1.3,<3.0.0)
Requires-Dist: pydantic (>=2.5.2,<3.0.0)
Requires-Dist: requests (>=2.31.0,<3.0.0)
Requires-Dist: ruamel-yaml (>=0.18.5,<0.19.0)
Requires-Dist: sqlalchemy (>=2.0.23,<3.0.0) ; extra == "sql" or extra == "duckdb"
Requires-Dist: starlette (>=0.36.3,<0.37.0)
Requires-Dist: tabulate (>=0.9.0,<0.10.0)
Requires-Dist: tiktoken (>=0.5.2,<0.6.0)
Requires-Dist: usearch (>=2.8.14,<3.0.0)
